yta_editor_parameters/__init__.py
yta_editor_parameters/abstract.py
yta_editor_parameters/constant.py
yta_editor_parameters/context/__init__.py
yta_editor_parameters/context/utils.py
yta_editor_parameters/eased.py
yta_editor_parameters/utils.py
yta_editor_parameters-0.0.8.dist-info/licenses/LICENSE
yta_editor_parameters-0.0.8.dist-info/METADATA
yta_editor_parameters-0.0.8.dist-info/WHEEL
yta_editor_parameters-0.0.8.dist-info/RECORD
