Metadata-Version: 2.4
Name: yta-editor-parameters
Version: 0.0.8
Summary: Youtube Autonomous Editor Parameters Module.
License-File: LICENSE
Author: danialcala94
Author-email: danielalcalavalera@gmail.com
Requires-Python: ==3.9
Classifier: Programming Language :: Python :: 3
Classifier: Programming Language :: Python :: 3.9
Requires-Dist: yta_parameters (>=0.0.1,<1.0.0)
Requires-Dist: yta_validation (>=0.0.1,<1.0.0)
